{
  "tests": {
    "lastSuccessfulRunSecs": 2,
    "lastSuccessfulRunAt": "2026-06-23T20:56:36.806684+00:00",
    "lastSuccessfulRunKind": "full",
    "recentRuns": [
      {
        "secs": 2,
        "at": "2026-06-23T20:56:36.806684+00:00",
        "kind": "full"
      },
      {
        "secs": 2,
        "at": "2026-06-23T20:25:55.529764+00:00",
        "kind": "full"
      },
      {
        "secs": 2,
        "at": "2026-06-23T19:10:27.658602+00:00",
        "kind": "full"
      },
      {
        "secs": 1,
        "at": "2026-06-23T18:43:53.692162+00:00",
        "kind": "full"
      },
      {
        "secs": 1,
        "at": "2026-06-22T23:54:45.675370+00:00",
        "kind": "full"
      },
      {
        "secs": 3,
        "at": "2026-06-22T23:27:33.901829+00:00",
        "kind": "full"
      },
      {
        "secs": 1,
        "at": "2026-06-22T23:25:51.551252+00:00",
        "kind": "full"
      },
      {
        "secs": 2,
        "at": "2026-06-22T19:58:38.079438+00:00",
        "kind": "full"
      },
      {
        "secs": 3,
        "at": "2026-06-22T19:38:01.547272+00:00",
        "kind": "full"
      }
    ]
  }
}